AUTHORS.rst
CONTRIBUTING.rst
HISTORY.rst
LICENSE
MANIFEST.in
README.rst
setup.cfg
setup.py
docs/Makefile
docs/authors.rst
docs/conf.py
docs/contributing.rst
docs/history.rst
docs/index.rst
docs/installation.rst
docs/make.bat
docs/readme.rst
docs/usage.rst
exreporter/__init__.py
exreporter/credentials.py
exreporter/formats.py
exreporter/reporter.py
exreporter/stack_trace.py
exreporter.egg-info/PKG-INFO
exreporter.egg-info/SOURCES.txt
exreporter.egg-info/dependency_links.txt
exreporter.egg-info/not-zip-safe
exreporter.egg-info/requires.txt
exreporter.egg-info/top_level.txt
exreporter/contrib/__init__.py
exreporter/contrib/django_middlewares.py
exreporter/stores/__init__.py
exreporter/stores/github.py
tests/__init__.py
tests/test_reporter.py