Metadata-Version: 1.1
Name: exreporter
Version: 0.1.3
Summary: Report Internal Server Errors as Issues
Home-page: https://github.com/vedarthk/exreporter
Author: Vedarth Kulkarni
Author-email: vedarthk@vedarthz.in
License: MIT
Keywords: exreporter
Platform: UNKNOWN
Classifier: Development Status :: 3 - Alpha
Classifier: Intended Audience :: Developers
Classifier: License :: OSI Approved :: MIT License
Classifier: Natural Language :: English
Classifier: Programming Language :: Python :: 2.7
